js_dl/__init__.py
js_dl/js_dl.py
js_dl-0.0.2.dist-info/LICENSE
js_dl-0.0.2.dist-info/METADATA
js_dl-0.0.2.dist-info/WHEEL
js_dl-0.0.2.dist-info/entry_points.txt
js_dl-0.0.2.dist-info/top_level.txt
js_dl-0.0.2.dist-info/RECORD
