Metadata-Version: 2.1
Name: js-dl
Version: 0.0.2
Summary: Download javascript libraries  from https://cdnjs.com
Home-page: https://github.com/rand-net/js-dl
Author: rand-net
License: MIT
Keywords: cdnjs,javascript,javascript libraries
Platform: UNKNOWN
Classifier: License :: OSI Approved :: MIT License
Classifier: Programming Language :: Python :: 3
Classifier: Programming Language :: Python :: 3.7
Requires-Dist: art
Requires-Dist: prompt-toolkit
Requires-Dist: requests
